{
  "file_globs": [
    "assets/public/static/js/*.js",
    "assets/public/static/css/*.css",
    "assets/public/index.html",
    "assets/public/manifest.json"
  ],
  "scan_file_globs": [
    "assets/public/static/js/*.js",
    "assets/public/index.html",
    "assets/public/asset-manifest.json",
    "assets/public/manifest.json"
  ],
  "string_blocklist": [
    "admob",
    "doubleclick.net",
    "gdt",
    "pangle",
    "bytedance"
  ],
  "regex_rewrites": [
    {
      "name": "disable_ad_init_common",
      "pattern": "(?s)\\b(initAd|initAds|loadAd|loadAds)\\s*\\(",
      "replace": "(function(){return;})("
    },
    {
      "name": "rename_custom_ad",
      "pattern": "custom_ad",
      "replace": "cover_default"
    },
    {
      "name": "disable_ad_component_force_hide",
      "pattern": "z=!0===\\(null===j\\|\\|void 0===j\\?void 0:j\\.ad_free\\)&&!S\\.includes\\(G\\)",
      "replace": "z=!0"
    },
    {
      "name": "disable_ad_component_initial_state",
      "pattern": "\\(0,l\\.S0\\)\\(3e3\\),k=\\(0,o\\.useRef\\)\\(null\\),\\[q,w\\]=\\(0,o\\.useState\\)\\(!1\\)",
      "replace": "(0,l.S0)(3e3),k=(0,o.useRef)(null),[q,w]=(0,o.useState)(!0)"
    },
    {
      "name": "disable_ad_component_render_gate",
      "pattern": "children:!q&&F&&null!==\\(null===F\\|\\|void 0===F\\?void 0:F\\.advs\\)",
      "replace": "children:!1&&F&&null!==(null===F||void 0===F?void 0:F.advs)"
    },
    {
      "name": "disable_ads_cache_read",
      "pattern": "i=JSON\\.parse\\(localStorage\\.getItem\\(\\\"adsList\\\"\\)\\)\\|\\|\\{\\}",
      "replace": "i={}"
    },
    {
      "name": "disable_ads_cache_write",
      "pattern": "localStorage\\.setItem\\(\\\"adsList\\\",JSON\\.stringify\\(a\\)\\)",
      "replace": "0"
    },
    {
      "name": "disable_ads_content_cache_write",
      "pattern": "localStorage\\.setItem\\(\\\"adsContent\\\",JSON\\.stringify\\(n\\.data\\)\\)",
      "replace": "0"
    },
    {
      "name": "disable_cover_ads_content_usage",
      "pattern": "p=localStorage\\.getItem\\(\\\"adsContent\\\"\\),f=p\\?JSON\\.parse\\(p\\):Object\\.keys\\(g\\|\\|\\{\\}\\)\\.length>0\\?g:\\{\\}",
      "replace": "p=localStorage.getItem(\"adsContent\"),f={}"
    },
    {
      "name": "disable_thewayhome_route_keylist",
      "pattern": "h=\\[\\\"app_thewayhome\\\"\\]",
      "replace": "h=[]"
    },
    {
      "name": "disable_feed_inline_ads_1",
      "pattern": "!r\\.ad_free&&i>0&&i%10===0",
      "replace": "!1"
    },
    {
      "name": "disable_feed_inline_ads_2",
      "pattern": "!s\\.ad_free&&\\(t\\+1\\)%10===1&&0!==t",
      "replace": "!1"
    },
    {
      "name": "mark_title_adfree",
      "pattern": "<title>JMComic3</title>",
      "replace": "<title>JMComic3 AdFree</title>"
    },
    {
      "name": "mark_manifest_adfree",
      "pattern": "\"name\": \"JMComic3\"",
      "replace": "\"name\": \"JMComic3 AdFree\""
    },
    {
      "name": "mark_manifest_shortname_adfree",
      "pattern": "\"short_name\": \"JMComic3\"",
      "replace": "\"short_name\": \"JMComic3 AdFree\""
    },
    {
      "name": "disable_clarity_loader",
      "pattern": "\"localhost\"===window\\.location\\.hostname\\|\\|window\\.location\\.href\\.includes\\(\"devapp\"\\)\\|\\|function",
      "replace": "\"localhost\"===window.location.hostname||true||function"
    },
    {
      "name": "remove_clarity",
      "pattern": "c\\.src=\\\"https://www\\\\.clarity\\\\.ms/tag/[^\\\"]+\\\",\\(i=e\\.getElementsByTagName\\(o\\)\\[0\\]\\)\\.parentNode\\.insertBefore\\(c,i\\)",
      "replace": "0"
    }
  ],
  "resource_drop_globs": [
    "assets/public/images/*ad*.*",
    "assets/public/images/custom_ad.*"
  ]
}
